usso/__init__.py
usso/api_key.py
usso/auth.py
usso/authorization.py
usso/config.py
usso/enums.py
usso/exceptions.py
usso/py.typed
usso/schemas.py
usso/user.py
usso/client/__init__.py
usso/client/async_client.py
usso/client/base_client.py
usso/client/client.py
usso/integrations/django/__init__.py
usso/integrations/django/middleware.py
usso/integrations/fastapi/__init__.py
usso/integrations/fastapi/dependency.py
usso/integrations/fastapi/handler.py
usso/utils/__init__.py
usso/utils/agent.py
usso/utils/string_utils.py
usso/utils/validators.py
usso-0.29.15.dist-info/licenses/LICENSE.txt
usso-0.29.15.dist-info/METADATA
usso-0.29.15.dist-info/WHEEL
usso-0.29.15.dist-info/entry_points.txt
usso-0.29.15.dist-info/top_level.txt
usso-0.29.15.dist-info/RECORD
