Metadata-Version: 2.4
Name: usso
Version: 0.29.15
Summary: A plug-and-play client for integrating universal single sign-on (SSO) with Python frameworks, enabling secure and seamless authentication across microservices.
Author-email: Mahdi Kiani <mahdikiany@gmail.com>
Maintainer-email: Mahdi Kiani <mahdikiany@gmail.com>
License-Expression: MIT
Project-URL: Homepage, https://github.com/ussoio/usso-python
Project-URL: Bug Reports, https://github.com/ussoio/usso-python/issues
Project-URL: Funding, https://github.com/ussoio/usso-python
Project-URL: Say Thanks!, https://saythanks.io/to/mahdikiani
Project-URL: Source, https://github.com/ussoio/usso-python
Keywords: usso,sso,authentication,security,fastapi,django
Classifier: Development Status :: 3 - Alpha
Classifier: Intended Audience :: Developers
Classifier: Topic :: Software Development :: Build Tools
Classifier: Programming Language :: Python :: 3
Classifier: Programming Language :: Python :: 3.10
Classifier: Programming Language :: Python :: 3.11
Classifier: Programming Language :: Python :: 3.12
Classifier: Programming Language :: Python :: 3 :: Only
Requires-Python: >=3.9
License-File: LICENSE.txt
Requires-Dist: pydantic>=2
Requires-Dist: cryptography>=43.0.0
Requires-Dist: cachetools
Requires-Dist: aiocache
Requires-Dist: singleton_package
Requires-Dist: json-advanced
Requires-Dist: httpx
Requires-Dist: usso-jwt>=0.2.10
Provides-Extra: fastapi
Requires-Dist: fastapi>=0.65.0; extra == "fastapi"
Requires-Dist: uvicorn[standard]>=0.13.0; extra == "fastapi"
Provides-Extra: django
Requires-Dist: Django>=3.2; extra == "django"
Provides-Extra: dev
Requires-Dist: check-manifest; extra == "dev"
Requires-Dist: pytest; extra == "dev"
Requires-Dist: pytest_asyncio; extra == "dev"
Provides-Extra: test
Requires-Dist: coverage; extra == "test"
Provides-Extra: validator
Requires-Dist: email-validator; extra == "validator"
Requires-Dist: phonenumbers; extra == "validator"
Provides-Extra: all
Requires-Dist: fastapi>=0.65.0; extra == "all"
Requires-Dist: uvicorn[standard]>=0.13.0; extra == "all"
Requires-Dist: Django>=3.2; extra == "all"
Requires-Dist: check-manifest; extra == "all"
Requires-Dist: pytest; extra == "all"
Requires-Dist: pytest_asyncio; extra == "all"
Requires-Dist: coverage; extra == "all"
Dynamic: license-file
